Compiled from "Outer.java"
class com.xujun.base.classp.Outer$1Inner {
  final java.lang.String val$a;

  final com.xujun.base.classp.Outer this$0;

  com.xujun.base.classp.Outer$1Inner();
    Code:
       0: aload_0
       1: aload_1
       2: putfield      #1                  // Field this$0:Lcom/xujun/base/classp/Outer;
       5: aload_0
       6: aload_2
       7: putfield      #2                  // Field val$a:Ljava/lang/String;
      10: aload_0
      11: invokespecial #3                  // Method java/lang/Object."<init>":()V
      14: return

  public void function();
    Code:
       0: getstatic     #4                  // Field java/lang/System.out:Ljava/io/PrintStream;
       3: aload_0
       4: getfield      #2                  // Field val$a:Ljava/lang/String;
       7: invokevirtual #5                  // Method java/io/PrintStream.println:(Ljava/lang/String;)V
      10: return
}
