Compiled from "Outer.java"
public class com.xujun.base.classp.Outer {
  public com.xujun.base.classp.Outer();
    Code:
       0: aload_0
       1: invokespecial #1                  // Method java/lang/Object."<init>":()V
       4: return

  public void print(java.lang.String);
    Code:
       0: new           #2                  // class com/xujun/base/classp/Outer$1Inner
       3: dup
       4: aload_0
       5: aload_1
       6: invokespecial #3                  // Method com/xujun/base/classp/Outer$1Inner."<init>":(Lcom/xujun/base/classp/Outer;Ljava/lang/String;)V
       9: invokevirtual #4                  // Method com/xujun/base/classp/Outer$1Inner.function:()V
      12: return

  public static void main(java.lang.String[]);
    Code:
       0: new           #5                  // class com/xujun/base/classp/Outer
       3: dup
       4: invokespecial #6                  // Method "<init>":()V
       7: ldc           #7                  // String world
       9: invokevirtual #8                  // Method print:(Ljava/lang/String;)V
      12: return
}
