Compiled from "FinalClassVar.java"
public class com.xujun.base.keywords.finalk.FinalClassVar {
  public com.xujun.base.keywords.finalk.FinalClassVar();
    Code:
       0: aload_0
       1: invokespecial #1                  // Method java/lang/Object."<init>":()V
       4: return

  public static void main(java.lang.String[]);
    Code:
       0: getstatic     #2                  // Field java/lang/System.out:Ljava/io/PrintStream;
       3: new           #3                  // class java/lang/StringBuilder
       6: dup
       7: invokespecial #4                  // Method java/lang/StringBuilder."<init>":()V
      10: ldc           #5                  // String FinalClassVar.num :
      12: invokevirtual #6                  // Method java/lang/StringBuilder.append:(Ljava/lang/String;)Ljava/lang/StringBuilder;
      15: getstatic     #7                  // Field num:I
      18: invokevirtual #8                  // Method java/lang/StringBuilder.append:(I)Ljava/lang/StringBuilder;
      21: invokevirtual #9                  // Method java/lang/StringBuilder.toString:()Ljava/lang/String;
      24: invokevirtual #10                 // Method java/io/PrintStream.println:(Ljava/lang/String;)V
      27: getstatic     #2                  // Field java/lang/System.out:Ljava/io/PrintStream;
      30: new           #3                  // class java/lang/StringBuilder
      33: dup
      34: invokespecial #4                  // Method java/lang/StringBuilder."<init>":()V
      37: ldc           #11                 // String FinalClassVar.num2:
      39: invokevirtual #6                  // Method java/lang/StringBuilder.append:(Ljava/lang/String;)Ljava/lang/StringBuilder;
      42: getstatic     #12                 // Field num2:I
      45: invokevirtual #8                  // Method java/lang/StringBuilder.append:(I)Ljava/lang/StringBuilder;
      48: invokevirtual #9                  // Method java/lang/StringBuilder.toString:()Ljava/lang/String;
      51: invokevirtual #10                 // Method java/io/PrintStream.println:(Ljava/lang/String;)V
      54: return

  static {};
    Code:
       0: ldc           #13                 // String 修饰类静态变量
       2: invokevirtual #14                 // Method java/lang/String.length:()I
       5: putstatic     #7                  // Field num:I
       8: ldc           #15                 // String 类静态变量在静态块中赋值
      10: invokevirtual #14                 // Method java/lang/String.length:()I
      13: putstatic     #12                 // Field num2:I
      16: return
}
