Compiled from "FinalLocalVar.java"
public class com.xujun.base.keywords.finalk.FinalLocalVar {
  public com.xujun.base.keywords.finalk.FinalLocalVar();
    Code:
       0: aload_0
       1: invokespecial #1                  // Method java/lang/Object."<init>":()V
       4: return

  public static void main(java.lang.String[]);
    Code:
       0: getstatic     #2                  // Field java/lang/System.out:Ljava/io/PrintStream;
       3: iconst_5
       4: invokevirtual #3                  // Method java/io/PrintStream.println:(I)V
       7: return
}

// 没有final修饰num时
Compiled from "FinalLocalVar2.java"
public class com.xujun.base.keywords.finalk.FinalLocalVar2 {
  public com.xujun.base.keywords.finalk.FinalLocalVar2();
    Code:
       0: aload_0
       1: invokespecial #1                  // Method java/lang/Object."<init>":()V
       4: return

  public static void main(java.lang.String[]);
    Code:
       0: iconst_5
       1: istore_1
       2: getstatic     #2                  // Field java/lang/System.out:Ljava/io/PrintStream;
       5: iload_1
       6: invokevirtual #3                  // Method java/io/PrintStream.println:(I)V
       9: return
}
